{
  "wellness": [
    {
      "image": "https://d18zdz9g6n5za7.cloudfront.net/wellness-videos/640/640-68-meditation-to-prepare-for-childbirth-9834.jpg",
      "text": "Meditation to Prepare for Childbirth",
      "para": "Mindfulness Practice for Pregnancy",
      "time": "12 Min-Mental Wellness",
      "type": "Free",
      "video": "https://www.youtube.com/embed/6DO0whpB44I"
    },
    {
      "image": "https://d18zdz9g6n5za7.cloudfront.net/wellness-videos/640/640-65-bedtime-stress-reduction-9b19.jpg",
      "text": "Bedtime Stress Reduction",
      "para": "Guided Meditation for Better Sleep",
      "time": "20 Min-Mental Wellness",
      "type": "Paid",
      "video": "https://www.youtube.com/embed/fcN37TxBE_s"
    },
    {
      "image": "https://d18zdz9g6n5za7.cloudfront.net/wellness-videos/640/640-67-guided-practice-to-embrace-vulnerability-96cb.jpg",
      "text": "Guided Practice Embrace Vulnerability",
      "para": "Fear of Vulnerability",
      "time": "10 Min-Guided Meditation",
      "type": "Free",
      "video": "https://www.youtube.com/embed/cZnsLVArIt8"
    },
    {
      "image": "https://d18zdz9g6n5za7.cloudfront.net/wellness-videos/640/640-66-soothing-meditation-to-get-back-to-sleep-bc83.jpg",
      "text": "Soothing Meditation to Get Back to Sleep",
      "para": "10-Minute Guided Practice for Sleep",
      "time": "10 Min-Guided Meditaiton",
      "type": "Paid",
      "video": "https://www.youtube.com/watch?v=qWy_aOlB45Y"
    },
    {
      "image": "https://d18zdz9g6n5za7.cloudfront.net/wellness-videos/640/640-64-guided-meditation-for-grief-9028.jpg",
      "text": "Guided Meditaion for Grief",
      "para": "Mindfulness Practice for Coping with Loss",
      "time": "15 Min - Guided Meditation",
      "type": "Free",
      "video": "https://www.youtube.com/watch?v=PYCr8dcmZyg"
    },
    {
      "image": "https://d18zdz9g6n5za7.cloudfront.net/wellness-videos/640/640-62-guided-meditation-for-caregivers-a4f8.jpg",
      "text": "Guided Meditaion for Caregivers",
      "para": "Mindfulness Practice for Self-Care",
      "time": "12 Min-Guided Meditation",
      "type": "Paid",
      "video": "https://www.youtube.com/watch?v=6DO0whpB44I"
    },
    {
      "image": "https://d18zdz9g6n5za7.cloudfront.net/wellness-videos/640/640-63-mindfulness-meditation-to-enhance-motivation-a0fe.jpg",
      "text": "Mindfulness Meditaion to Enhance Motivation",
      "pare": "15-Minute Guided Practice to Boost Motivation",
      "time": "15 Min-Guided Meditation",
      "type": "Free",
      "video": "https://www.youtube.com/watch?v=fcN37TxBE_s"
    },
    {
      "image": "https://d18zdz9g6n5za7.cloudfront.net/wellness-videos/640/640-37-control-your-breath-with-pursed-lip-breathing-99ce.jpg",
      "text": "Control Your Breath With Pursed Lip Breathing",
      "para": "Guided Breathing Technique",
      "time": "10 Min-Guided Meditation",
      "type": "Paid",
      "video": "https://www.youtube.com/watch?v=cZnsLVArIt8"
    },
    {
      "image": "https://d18zdz9g6n5za7.cloudfront.net/wellness-videos/640/640-61-30-minute-guided-walking-meditation-afbd.jpg",
      "text": "30-Minute Guided Walking Meditation",
      "para": "Mindfulness Practice with Movement",
      "time": "30 Min-Mindfulness",
      "type": "Free",
      "video": "https://www.youtube.com/watch?v=qWy_aOlB45Y"
    },
    {
      "image": "https://d18zdz9g6n5za7.cloudfront.net/wellness-videos/640/640-60-5-minute-mindfulness-work-break-847e.jpg",
      "text": "5-Minute Mindfulness Work Break",
      "para": "Quick Guided Meditation to Recenter",
      "time": "15 Min-Guided Meditation",
      "type": "Paid",
      "video": "https://www.youtube.com/watch?v=PYCr8dcmZyg"
    },
    {
      "image": "https://d18zdz9g6n5za7.cloudfront.net/wellness-videos/640/640-43-meditation-to-manage-judgment-aa86.jpg",
      "text": "Meditation to Manage Judgment",
      "para": "Mindfulness Practice for Non-Judgmental Awareness",
      "time": "11 Min-Guided Meditaion",
      "type": "Free",
      "video": "https://www.youtube.com/watch?v=qWy_aOlB45Y"
    },
    {
      "image": "https://d18zdz9g6n5za7.cloudfront.net/wellness-videos/640/640-59-meditation-for-self-compassion-bf2b.jpg",
      "text": "Meditation for Self-Compassion",
      "para": "Guided Practice for Positive Self-Talk",
      "time": "15 Min-Guided Meditation",
      "type": "Paid",
      "video": "https://d18zdz9g6n5za7.cloudfront.net/blog/640/640-1081-shakshuka-breakfast-pizza-aea2.jpg"
    },
    {
      "image": "https://d18zdz9g6n5za7.cloudfront.net/wellness-videos/640/640-28-mindfulness-practice-for-forgiveness-af83.jpg",
      "text": "Mindfulness Practice for Forgiveness",
      "para": "Release Negative Emotions",
      "time": "10 Min-Guided Meditaiton",
      "type": "Free",
      "video": "https://www.youtube.com/watch?v=cZnsLVArIt8"
    },
    {
      "image": "https://d18zdz9g6n5za7.cloudfront.net/wellness-videos/640/640-41-guided-slow-breathing-practice-a5d1.jpg",
      "text": "Guided Slow Breathing Practice",
      "para": "Stress-Reducing Breathing Technique",
      "time": "15 Min-Guided Meditation",
      "type": "Paid",
      "video": "https://www.youtube.com/watch?v=cZnsLVArIt8"
    },
    {
      "image": "https://d18zdz9g6n5za7.cloudfront.net/wellness-videos/640/640-44-energizing-mindfulness-practice-8b10.jpg",
      "text": "Energizing Mindfullness Practice",
      "para": "Energy Boosting Guided Meditation",
      "time": "11 Min-Guided Meditaion",
      "type": "Free",
      "video": "https://d18zdz9g6n5za7.cloudfront.net/blog/640/640-1081-shakshuka-breakfast-pizza-aea2.jpg"
    },
    {
      "image": "https://d18zdz9g6n5za7.cloudfront.net/wellness-videos/640/640-36-pre-workout-guided-visualization-8990.jpg",
      "text": "Pre-Workout Guided Visualization",
      "para": "Enhance Athletic Performance with Motor Imagery",
      "time": "10 Min-Guided Meditaiton",
      "type": "Paid",
      "video": "https://www.youtube.com/watch?v=cZnsLVArIt8"
    },
    {
      "image": "https://d18zdz9g6n5za7.cloudfront.net/wellness-videos/640/640-33-guided-breathing-for-stress-relief-bf1f.jpg",
      "text": "Guided Breathing for Stress Relief",
      "para": "Nadi Shodhana Pranayama Technique",
      "time": "12 Min-Guided Meditation",
      "type": "Free",
      "video": "https://www.youtube.com/watch?v=cZnsLVArIt8"
    },
    {
      "image": "https://d18zdz9g6n5za7.cloudfront.net/wellness-videos/640/640-34-meditation-to-improve-concentration-a08b.jpg",
      "text": "Meditaion to Improve Concentration",
      "para": "Practice Focusing and Redirecting Your Attention",
      "time": "17 Min-Guided Meditation",
      "type": "Paid",
      "video": "https://www.youtube.com/watch?v=cZnsLVArIt8"
    },
    {
      "image": "https://d18zdz9g6n5za7.cloudfront.net/wellness-videos/640/640-26-visualization-for-emotional-healing-ba06.jpg",
      "text": "Visualization for Emotional healing",
      "para": "Inner Child Guided Practice",
      "time": "13 Min-Guided Meditation",
      "type": "Free",
      "video": "https://d18zdz9g6n5za7.cloudfront.net/blog/640/640-1081-shakshuka-breakfast-pizza-aea2.jpg"
    },
    {
      "image": "https://d18zdz9g6n5za7.cloudfront.net/wellness-videos/640/640-32-gratitude-meditation-9972.jpg",
      "text": "Gratitude Meditation",
      "para": "Guided Practice to Boost Appreciation",
      "time": "16 Min-Guided Meditation",
      "type": "Paid",
      "video": "https://www.youtube.com/watch?v=cZnsLVArIt8"
    }
  ]
}
